Workbook

Sheet 📊 Results
A1: Alpha ID | B1: Name | C1: Universe | D1: Sharpe | E1: Fitness | F1: TO % | G1: Max Corr | H1: Status | I1: Rejection Reason | J1: Date Submitted | K1: Notes | L1: Expression
A2: A1 | B2: Volatility Reversal | C2: TOP3000 | D2: 1.45 | E2: 0.78 | F2: 40 | G2: =IFERROR(MAX(Y2:AA2),"") -> 0 | H2: ❌ Rejected | I2: Fitness Block | K2: Signal decays rapidly. Pure vol signals fully arbitraged. | L2: -rank(ts_std_dev(returns,20))
A3: A2 | B3: Vol-Normalized Momentum | C3: TOP3000 | D3: 1.45 | E3: 0.78 | F3: 40 | G3: =IFERROR(MAX(Y3:AA3),"") -> 0 | H3: ❌ Rejected | I3: Fitness Block | K3: Simple delta has signal but Fitness <1.0. Needs second ingredient. | L3: -rank(ts_delta(close,5))
A4: A3 | B4: Vol-Ratio Reversal | C4: TOP3000 | D4: 1.02 | E4: 0.42 | F4: 42 | G4: =IFERROR(MAX(Y4:AA4),"") -> 0 | H4: ❌ Rejected | I4: Train/Test Overfit | K4: Train-Test gap >0.5 = disqualifying overfit. | L4: -rank(ts_corr(close,volume,10)/ts_std_dev(returns,20))
A5: A4 | B5: P/S Momentum | C5: TOP3000 | D5: 1.71 | E5: 1.37 | F5: 23.93 | G5: =IFERROR(MAX(Y5:AA5),"") -> 0 | H5: ✅ Submitted | K5: Template alpha. sales_ps most reliable fundamental found. | L5: -rank(ts_decay_linear(close/sales_ps,21)*rank(ts_delta(close,5)))
A6: A5 | B6: Bookvalue Momentum | C6: TOP3000 | D6: 1.07 | E6: 0.62 | F6: 22 | G6: =IFERROR(MAX(Y6:AA6),"") -> 0 | H6: ❌ Rejected | I6: 2021-2022 Collapse | K6: bookvalue_ps weaker than sales_ps. Distorted by buybacks. | L6: -rank(ts_decay_linear(close/bookvalue_ps,21)*rank(ts_delta(close,5)))
A7: A6 | B7: Sales Delta | C7: TOP3000 | D7: -0.35 | F7: 5.74 | G7: =IFERROR(MAX(Y7:AA7),"") -> 0 | H7: ❌ Rejected | I7: Dead Signal | K7: Pure fundamental momentum fails alone. Too slow, too low TO. | L7: -rank(ts_delta(sales_ps,63))
A8: A7 | B8: EV/EBITDA Reversion | C8: TOP3000 | D8: 1.19 | E8: 0.6 | F8: 10 | G8: =IFERROR(MAX(Y8:AA8),"") -> 0 | H8: ❌ Rejected | I8: 2021-2022 Collapse | K8: Train>>Test overfit. 2021/2022 both negative = dead. | L8: -ts_zscore(enterprise_value/ebitda,63)
A9: A8 | B9: Vol-Corr Momentum | C9: TOP3000 | D9: 0.6 | E9: 0.3 | F9: 40 | G9: =IFERROR(MAX(Y9:AA9),"") -> 0 | H9: ❌ Rejected | I9: Dead Signal | K9: No consistent signal. ts_corr highly unstable Train/Test. | L9: -rank(ts_corr(returns,volume,10))
A10: A9 | B10: Price Reversal × Volume | C10: TOP3000 | D10: 2.01 | E10: 1 | F10: 61.29 | G10: =IFERROR(MAX(Y10:AA10),"") -> 0 | H10: ✅ Submitted | K10: Best IS Sharpe submitted. Turnover high but passed Fitness=1.00. | L10: -rank(ts_delta(close,1)*ts_rank(volume,5))
A11: A10 | B11: Liquidity Momentum | C11: TOP3000 | D11: 1.93 | E11: 1.31 | F11: 28.66 | G11: =IFERROR(MAX(Y11:AA11),"") -> 0 | H11: ✅ Submitted | K11: current_ratio rare working fundamental. Delay 1 only. | L11: -rank(ts_decay_linear(current_ratio,21)*rank(ts_delta(close,5)))
A12: A11 | B12: Return Assets Momentum | C12: TOP3000 | D12: -0.12 | F12: 7.24 | G12: =IFERROR(MAX(Y12:AA12),"") -> 0 | H12: ❌ Rejected | I12: 2021-2022 Collapse | K12: Negative IS. return_assets COVID-distorted. | L12: -rank(ts_decay_linear(close/return_assets,21)*rank(ts_delta(close,20)))
A13: A12 | B13: EBIT/CAPEX Efficiency | C13: TOP3000 | D13: -0.13 | F13: 1.94 | G13: =IFERROR(MAX(Y13:AA13),"") -> 0 | H13: ❌ Rejected | I13: Dead Signal | K13: Negative IS. External PDF claimed 1.62 Sharpe — unverifiable. | L13: -rank(ebit/capex)
A14: A13 | B14: CLV Reversion | C14: TOP3000 | D14: 2.1 | E14: 0.96 | F14: 60 | G14: =IFERROR(MAX(Y14:AA14),"") -> 0 | H14: ❌ Rejected | I14: Fitness Block | K14: Best IS Sharpe overall but 60% TO creates structural Fitness ceiling. | L14: -rank(((2*close-high-low)/(high-low))*ts_rank(volume,5))
A15: A14 | B15: CLV+Volume/ADV20 | C15: TOP3000 | D15: 2.03 | E15: 0.99 | F15: 60 | G15: =IFERROR(MAX(Y15:AA15),"") -> 0 | H15: ❌ Rejected | I15: Fitness Block | K15: Same family as A13. 60% TO ceiling confirmed structural. | L15: -rank(((2*close-high-low)/(high-low))*volume/adv20)
A16: A15 | B16: ADV20 Reversion | C16: TOP3000 | D16: 2.08 | E16: 0.87 | F16: 85 | G16: =IFERROR(MAX(Y16:AA16),"") -> 0 | H16: ❌ Rejected | I16: Turnover Too High | K16: 85% turnover. Fitness penalizes >60% TO structurally. | L16: -rank(ts_delta(close,1)/adv20)
A17: A16 | B17: Price Delta × Volume v2 | C17: TOP3000 | D17: 1.81 | E17: 1.01 | F17: 48 | G17: =IFERROR(MAX(Y17:AA17),"") -> 0 | H17: ❌ Rejected | I17: Self-Correlation | K17: 0.96 vs A9. Minor delta change = same portfolio. | L17: -rank(ts_delta(close,2)*ts_rank(volume,10))
A18: A17 | B18: VWAP Zscore × Volume | C18: TOP3000 | D18: 2.1 | E18: 0.81 | F18: 63 | G18: =IFERROR(MAX(Y18:AA18),"") -> 0 | H18: ❌ Rejected | I18: Fitness Block | K18: 63% TO. Same ceiling as CLV family. Abandoned family. | L18: -rank(ts_zscore(close-vwap,20)*ts_rank(volume,5))
A19: A18 | B19: Current Ratio (Market Neut) | C19: TOP3000 | D19: 1.32 | E19: 1.07 | F19: 24 | G19: =IFERROR(MAX(Y19:AA19),"") -> 0 | H19: ❌ Rejected | I19: Self-Correlation | K19: 0.84 vs A10. Same variable = same correlation regardless of settings. | L19: -rank(ts_decay_linear(current_ratio,21)*rank(ts_delta(close,5)))
A20: A19 | B20: Momentum Up-Days | C20: TOP3000 | D20: 1.5 | E20: 0.78 | F20: 37 | G20: =IFERROR(MAX(Y20:AA20),"") -> 0 | H20: ❌ Rejected | I20: Fitness Block | K20: Signal exists but Fitness ceiling. 37% TO insufficient returns. | L20: rank(ts_sum(returns>0?1:0,250))
A21: A20 | B21: ts_arg_max Reversion | C21: TOP3000 | D21: 1.41 | E21: 0.87 | F21: 50 | G21: =IFERROR(MAX(Y21:AA21),"") -> 0 | H21: ❌ Rejected | I21: 2021-2022 Collapse | K21: 2021 Sharpe 0.56-0.73. Structural weakness in 2021. | L21: (vwap-close)/close/min(ts_decay_linear(rank(ts_arg_max(close,30)),2),0.20)
A22: A21 | B22: IV Regime + A9 Signal | C22: TOP3000 | D22: 1.94 | E22: 1.01 | F22: 35 | G22: =IFERROR(MAX(Y22:AA22),"") -> 0 | H22: ❌ Rejected | I22: Self-Correlation | K22: IV filter confirmed working (threshold 0.3). Inner signal = A9 = 0.85 corr. | L22: trade_when(ts_rank(implied_volatility_call_60,252)>0.3,-rank(ts_delta(close,1)*ts_rank(volume,5)),-1)
A23: A22 | B23: IV + CLV Filter | C23: TOP3000 | D23: 1.59 | E23: 0.75 | F23: 34 | G23: =IFERROR(MAX(Y23:AA23),"") -> 0 | H23: ❌ Rejected | I23: Fitness Block | K23: CLV without volume loses too much signal. Fitness 0.75. | L23: trade_when(ts_rank(implied_volatility_call_60,252)>0.3,-rank((2*close-high-low)/(high-low)),-1)
A24: A23 | B24: IV + Current Ratio Filter | C24: TOP3000 | D24: 1.96 | E24: 1.46 | F24: 22 | G24: =IFERROR(MAX(Y24:AA24),"") -> 0 | H24: ❌ Rejected | I24: Self-Correlation | K24: 0.9445 vs A10. Same var = same corr. Need different data source. | L24: trade_when(ts_rank(implied_volatility_call_60,252)>0.3,-rank(ts_decay_linear(current_ratio,21)*rank(ts_delta(close,5))),-1)
A25: A24 | B25: Debt/Equity Momentum | C25: TOP3000 | D25: -0.24 | F25: 16 | G25: =IFERROR(MAX(Y25:AA25),"") -> 0 | H25: ❌ Rejected | I25: 2021-2022 Collapse | K25: COVID stimulus broke leverage signals. 2021 Sharpe -1.19. | L25: -rank(ts_decay_linear(debt/equity,21)*rank(ts_delta(close,5)))
A26: A25 | B26: Debt/Assets Ratio | C26: TOP3000 | D26: -1.22 | F26: 2.64 | G26: =IFERROR(MAX(Y26:AA26),"") -> 0 | H26: ❌ Rejected | I26: 2021-2022 Collapse | K26: Negative every year. COVID distorted all leverage signals. | L26: -rank(debt/assets)
A27: A26 | B27: Social Buzz Momentum | C27: TOP3000 | D27: 1.4 | E27: 0.56 | F27: 48.63 | G27: =IFERROR(MAX(Y27:AA27),"") -> 0 | H27: ❌ Rejected | I27: Fitness Ceiling | K27: snt_buzz family: 10+ variants, IS Fitness ceiling 0.98. Permanently abandoned. Signal inverted (must use +rank not -rank). | L27: -rank(ts_decay_linear(scl12_buzz,21)*rank(ts_delta(close,5)))
A28: A27 | B28: OEY ts_rank | C28: TOP3000 | F28: 10 | G28: =IFERROR(MAX(Y28:AA28),"") -> 0 | H28: ❌ Rejected | I28: 2021-2022 Collapse | K28: operating_income unavailable or 2021-2022 collapse. Tutorial Sharpe unverifiable. | L28: -rank(ts_rank(operating_income/cap,250))
A29: A28 | B29: Range Momentum | C29: TOP3000 | D29: -0.08 | F29: 8 | G29: =IFERROR(MAX(Y29:AA29),"") -> 0 | H29: ❌ Rejected | I29: Dead Signal | K29: 2020 Sharpe -2.57. Extreme COVID vol sensitivity. | L29: rank(ts_mean(high-low,20)/ts_mean(high-low,252))
A30: A29 | B30: Open-Close Reversion | C30: TOP3000 | D30: -1.22 | F30: 26 | G30: =IFERROR(MAX(Y30:AA30),"") -> 0 | H30: ❌ Rejected | I30: Dead Signal | K30: Consistently negative every year. No persistent cross-sectional signal. | L30: -rank(ts_mean(close-open,10))
A31: A30 | B31: Earnings Revision Filter | C31: TOP3000 | D31: -0.57 | F31: 12 | G31: =IFERROR(MAX(Y31:AA31),"") -> 0 | H31: ❌ Rejected | I31: Dead Signal | K31: 56% coverage kills sub-universe Sharpe. Analyst fields too sparse. | L31: trade_when(snt1_d1_netearningsrevision>0,rank(ts_delta(close,5)),-1)
A32: MC3 | B32: Value Rank ts_rank(252) | C32: TOP3000 | D32: 1.89 | E32: 1.66 | F32: 10.44 | G32: =IFERROR(MAX(Y32:AA32),"") -> 0 | H32: ✅ Submitted | J32: 05/04/2026 | K32: ts_rank(252) rescued value signal from 2020 crash. Near-zero corr with all submitted. Alpha 11. | L32: -rank(ts_rank(mdl177_garpanalystmodel_qgp_vfpriceratio,252))
A33: M6 | B33: CashFlow/EV ts_rank(252) | C33: TOP3000 | D33: 1.72 | E33: 1.22 | F33: 9.06 | G33: =IFERROR(MAX(Y33:AA33),"") -> 0 | H33: ✅ Submitted | J33: 05/04/2026 | K33: Most consistent yearly profile in tracker — all 5 years positive, min 1.41. Alpha 12. ts_rank(252) pattern confirmed for Model value family. | L33: -rank(ts_rank(mdl177_2_sensitivityfactor400_ttmocfev,252))
A34: Z1 | B34: Analyst Stock Rank Naked | C34: TOP3000 | D34: 0.36 | E34: 0.19 | F34: 4.09 | G34: =IFERROR(MAX(Y34:AA34),"") -> 0 | H34: ❌ Rejected | I34: 2021-2022 Collapse | K34: 2021/2022 regime failure. A4 template also failed (2021=0.00, 2022=-0.41). Two-test rule exhausted. Abandoned. | L34: -rank(snt1_d1_stockrank)
A35: Z2 | B35: scl12_sentiment Naked | C35: TOP3000 | D35: 0.58 | E35: 0.08 | F35: 86.03 | G35: =IFERROR(MAX(Y35:AA35),"") -> 0 | H35: ❌ Rejected | I35: Fitness Ceiling | K35: 86% TO makes Fitness mathematically impossible. Would need 93% returns for Fitness 1.0 at this Sharpe. Dead. | L35: -rank(scl12_sentiment)
A36: Z3 | B36: snt_buzz_ret Naked | C36: TOP3000 | D36: -0.27 | E36: -0.03 | F36: 62.83 | G36: =IFERROR(MAX(Y36:AA36),"") -> 0 | H36: ❌ Rejected | I36: Dead Signal | K36: Negative both signs. Flipped sign also dead. Abandoned. | L36: -rank(snt_buzz_ret)
A37: Z4 | B37: snt_social_value Naked | C37: TOP3000 | D37: -0.61 | E37: -0.13 | F37: 47.58 | G37: =IFERROR(MAX(Y37:AA37),"") -> 0 | H37: ❌ Rejected | I37: Dead Signal | K37: Negative both signs. Flipped also dead. Abandoned. | L37: -rank(snt_social_value)
A38: M1 | B38: Value-to-Price Rank Naked | C38: TOP3000 | D38: 1.09 | E38: 1.05 | F38: 3.07 | G38: =IFERROR(MAX(Y38:AA38),"") -> 0 | H38: ❌ Rejected | I38: Sharpe Below Cutoff | K38: IS Sharpe 1.09 below 1.25 cutoff. Sub-universe Sharpe 0.46 below 0.47 cutoff. Led to MC3 discovery. | L38: -rank(mdl177_garpanalystmodel_qgp_vfpriceratio)
A39: M4 | B39: CashFlow/EV Naked | C39: TOP3000 | D39: 0.66 | E39: 0.5 | F39: 2.64 | G39: =IFERROR(MAX(Y39:AA39),"") -> 0 | H39: ❌ Rejected | I39: 2021-2022 Collapse | K39: 2020 collapse -2.09. ts_rank(252) fix led to M6 submission. | L39: -rank(mdl177_2_sensitivityfactor400_ttmocfev)
A40: DV1 | B40: Current Earnings Yield ts_rank | C40: TOP3000 | D40: 1.04 | E40: 0.68 | F40: 9.46 | H40: ❌ Rejected | I40: Fitness Below Threshold | K40: IS 1.04, Fitness 0.68. All years positive except 2023 flat. Below Fitness threshold. | L40: -rank(ts_rank(mdl177_2_deepvaluefactor_curep,252))
A41: DV2 | B41: Forward 12m EP ts_rank | C41: TOP3000 | D41: 1.23 | E41: 0.87 | F41: 10.18 | G41: 0.5365 | H41: ❌ Rejected | I41: Train/Test Gap + Fitness | K41: IS 1.23, Fit 0.87. Train 0.03 huge gap. 2023 flat. Below threshold. Base for DV2c. | L41: -rank(ts_rank(mdl177_2_deepvaluefactor_fwdep,252))
A42: DV2b | B42: Forward 12m EP ts_rank(126) | C42: TOP3000 | D42: 1.14 | E42: 0.77 | F42: 13.12 | H42: ❌ Rejected | I42: Fitness Below Threshold | K42: Shorter window raised TO, no improvement. 2023 -0.38. | L42: -rank(ts_rank(mdl177_2_deepvaluefactor_fwdep,126))
A43: DV2c | B43: Forward 12m EP × Momentum | C43: TOP3000 | D43: 1.4 | E43: 1.06 | F43: 14.26 | G43: 0.5482 | J43: 05/06/2026 | K43: IS 1.40, Fit 1.06. All 5 years positive. Train 1.37 no gap. Max corr 0.5482 vs A9. | L43: -rank(ts_rank(mdl177_2_deepvaluefactor_fwdep,252)*rank(ts_delta(close,21)))
A44: DV4 | B44: EBITDA/EV ts_rank | C44: TOP3000 | D44: 0.72 | E44: 0.35 | F44: 9.07 | H44: ❌ Rejected | I44: Fitness Below Threshold | K44: IS 0.72, Fit 0.35. 2022/2023 weak. Dead. | L44: -rank(ts_rank(mdl177_2_deepvaluefactor_ebitdaev,252))
A45: DV5 | B45: TTM FCF/Price ts_rank | C45: TOP3000 | D45: 1.6 | E45: 1.11 | F45: 8.06 | G45: 0.5199 | J45: 05/07/2026 | K45: IS 1.60, Fit 1.11. All 5 years positive. Max corr 0.5199 vs M6. | L45: -rank(ts_rank(mdl177_2_deepvaluefactor_ttmfcfp,252))
A46: DV6 | B46: Book-to-Price ts_rank | C46: TOP3000 | D46: 0.26 | E46: 0.12 | F46: 9.46 | H46: ❌ Rejected | I46: 2021-2022 Collapse | K46: IS 0.26. 2021 -0.62, 2022 -0.22. Book value fails in growth regime. | L46: -rank(ts_rank(mdl177_2_deepvaluefactor_bp,252))
A47: DV7 | B47: Pro Forma EP ts_rank | C47: TOP3000 | D47: 0.69 | E47: 0.36 | F47: 9.31 | H47: ❌ Rejected | I47: 2023 Collapse | K47: IS 0.69. 2023 -0.51. Train -0.50 gap. | L47: -rank(ts_rank(mdl177_2_deepvaluefactor_proformaep,252))
A48: DV8 | B48: NAV/Price ts_rank | C48: TOP3000 | D48: 0.19 | E48: 0.07 | F48: 9.48 | H48: ❌ Rejected | I48: 2021-2022 Collapse | K48: IS 0.19. 2021 -0.39, 2022 -0.27. Dead. | L48: -rank(ts_rank(mdl177_2_deepvaluefactor_navp,252))
A49: DV9 | B49: Cash/Price ts_rank | C49: TOP3000 | D49: 0.48 | E49: 0.29 | F49: 8.33 | H49: ❌ Rejected | I49: 2022 Collapse | K49: IS 0.48. 2022 -0.28. Dead. | L49: -rank(ts_rank(mdl177_2_deepvaluefactor_cashp,252))
A50: DV10 | B50: Forward EPS/EV ts_rank | C50: TOP3000 | D50: 1.03 | E50: 0.66 | F50: 9.74 | H50: ❌ Rejected | I50: Fitness Below Threshold | K50: IS 1.03, Fit 0.66. 2020 -0.13, 2023 flat. Below threshold. | L50: -rank(ts_rank(mdl177_2_deepvaluefactor_f12mepssev,252))
A51: DV10b | B51: Forward EPS/EV × Momentum | C51: TOP3000 | D51: 1.31 | E51: 0.95 | F51: 14.09 | H51: ❌ Rejected | I51: Fitness Below Threshold | K51: IS 1.31, Fit 0.95. Just below threshold. | L51: -rank(ts_rank(mdl177_2_deepvaluefactor_f12mepssev,252)*rank(ts_delta(close,21)))
A52: DV3 | B52: TTM FCF/EV ts_rank | C52: TOP3000 | D52: 1.37 | E52: 0.86 | F52: 7.85 | H52: ❌ Rejected | I52: Fitness Below Threshold | K52: IS 1.37, Fit 0.86. All 5 years positive. Below threshold. Base for DV3b. | L52: -rank(ts_rank(mdl177_2_deepvaluefactor_ttmfcev,252))
A53: DV3b | B53: TTM FCF/EV × Momentum | C53: TOP3000 | D53: 1.67 | E53: 1.29 | F53: 12.79 | G53: 0.505 | J53: 05/08/2026 | K53: IS 1.67, Fit 1.29. All 5 years positive. Train 2.04 no overfit. Max corr 0.5050 vs M6. | L53: -rank(ts_rank(mdl177_2_deepvaluefactor_ttmfcev,252)*rank(ts_delta(close,21)))
A54: DV11 | B54: TTM OCF/Price ts_rank | C54: TOP3000 | D54: 1.64 | E54: 1.26 | F54: 8.98 | G54: 0.8994 | H54: ❌ Rejected | I54: Self-Correlation | K54: IS 1.64, Fit 1.26 — passes on metrics. Killed: corr 0.8994 vs M6. ttmocfp ≈ ttmocfev. | L54: -rank(ts_rank(mdl177_2_deepvaluefactor_ttmocfp,252))
A1001: M11 | B1001: 5yr RelValue ts_rank(252) | C1001: TOP3000 | D1001: 1.6 | E1001: 1.23 | F1001: 10.92 | G1001: =IFERROR(MAX(Y1001:AA1001),"") -> 0 | H1001: ✅ Submitted | J1001: 05/04/2026 | K1001: Submitted as Alpha 13. All years positive. Max corr 0.35 vs MC3. ts_rank(252) pattern confirmed again. | L1001: -rank(ts_rank(mdl177_2_5yearrelativevaluefactor_rel5yfwdep,252))
A1002: M10 | B1002: 5yr RelValue Naked | C1002: TOP3000 | D1002: 1.32 | E1002: 1 | F1002: 5.21 | G1002: =IFERROR(MAX(Y1002:AA1002),"") -> 0 | H1002: ✅ Submitted | J1002: 05/04/2026 | K1002: Submitted as Alpha 14. IS Fitness exactly 1.00. Max corr 0.59 vs M11. Near-zero corr 0.02 vs MC3. | L1002: -rank(mdl177_2_5yearrelativevaluefactor_rel5yfwdep)
A1003: M15b | B1003: Norm Earnings Yield ts_rank(252) | C1003: TOP3000 | D1003: 1.58 | E1003: 1.27 | F1003: 10.23 | G1003: =IFERROR(MAX(Y1003:AA1003),"") -> 0 | H1003: ✅ Submitted | J1003: 05/04/2026 | K1003: Submitted as Alpha 15. Max corr 0.57 vs M6. All 4 visible years positive. Test Sharpe 0.94 strong. | L1003: -rank(ts_rank(mdl177_2_sensitivityfactor400_ney,252))
A1004: M9 | B1004: CapEff ts_rank(252) | C1004: TOP3000 | D1004: 1.57 | E1004: 1.19 | F1004: 10.79 | G1004: =IFERROR(MAX(Y1004:AA1004),"") -> 0 | H1004: ❌ Rejected | I1004: Self-Corr 0.76 vs MC3 | K1004: IS stats pass but corr 0.7569 vs MC3 exceeds threshold. ts_rank(252) on same GARP family = structural similarity. Abandoned. | L1004: -rank(ts_rank(mdl177_2_garpanalystmodel_qgp_capeff,252))
A1005: M14b | B1005: FANGMA ts_rank(252) | C1005: TOP3000 | D1005: 1.84 | E1005: 1.57 | F1005: 10.49 | G1005: =IFERROR(MAX(Y1005:AA1005),"") -> 0 | H1005: ❌ Rejected | I1005: Self-Corr 0.99 vs MC3 | K1005: FANGMA composite = same signal as vfpriceratio. Corr 0.9903 vs MC3. Entire FANGMA variable family permanently abandoned. | L1005: -rank(ts_rank(mdl177_fangma_gpam_usa_fangma_gpam11,252))
A1006: M12b | B1006: ShortInt Chg12m ts_rank(252) | C1006: TOP3000 | D1006: -1 | E1006: -0.47 | F1006: 5.82 | G1006: =IFERROR(MAX(Y1006:AA1006),"") -> 0 | H1006: ❌ Rejected | I1006: Dead Signal | K1006: ts_rank made IS worse (naked -0.81 → ts_rank -1.00). Genuine signal reversal post-2021, not volatility distortion. Both signs exhausted. Permanently abandoned. | L1006: -rank(ts_rank(mdl177_2_sensitivityfactor400_chg12msip,252))
A1007: M13b | B1007: EarningsQuality Flipped Naked | C1007: TOP3000 | D1007: 1.04 | E1007: 0.53 | F1007: 3.17 | G1007: =IFERROR(MAX(Y1007:AA1007),"") -> 0 | H1007: ❌ Rejected | I1007: Fitness 0.53 | K1007: 2022 -0.68 blocker. IS Fitness 0.53. ts_rank version also dead (IS 0.11). Both signs and both operators exhausted. Abandoned. | L1007: rank(mdl177_2_earningsqualityfactor_uap)
A1008: M13c | B1008: EarningsQuality Flipped ts_rank(252) | C1008: TOP3000 | D1008: 0.11 | E1008: 0.02 | F1008: 6.45 | G1008: =IFERROR(MAX(Y1008:AA1008),"") -> 0 | H1008: ❌ Rejected | I1008: Dead Signal | K1008: 2022 structural reversal unfixable by ts_rank. IS Fitness 0.02. All operators exhausted on this variable. Permanently abandoned. | L1008: rank(ts_rank(mdl177_2_earningsqualityfactor_uap,252))
A1009: M15 | B1009: Norm Earnings Yield Naked | C1009: TOP3000 | D1009: 0.61 | E1009: 0.4 | F1009: 2.5 | G1009: =IFERROR(MAX(Y1009:AA1009),"") -> 0 | H1009: ❌ Rejected | I1009: 2020 Weakness | K1009: 2020 -0.75. ts_rank(252) fix led to M15b submission. | L1009: -rank(mdl177_2_sensitivityfactor400_ney)
A1010: M16 | B1010: Idiosyncratic Risk 360d ts_rank | C1010: TOP3000 | D1010: -1.45 | E1010: -0.84 | F1010: 26.2 | G1010: =IFERROR(MAX(Y1010:AA1010),"") -> 0 | H1010: ❌ Rejected | I1010: Dead Signal | K1010: Negative 2020-2023. Both risk family variables exhausted (90d and 360d). Permanently abandoned. | L1010: -rank(ts_rank(unsystematic_risk_last_360_days,252))
A1011: M17 | B1011: Beta SPY 60d Naked | C1011: TOP3000 | D1011: -0.01 | E1011: 0 | F1011: 15.13 | G1011: =IFERROR(MAX(Y1011:AA1011),"") -> 0 | H1011: ❌ Rejected | I1011: Dead Signal | K1011: IS Sharpe literally zero. Beta signal broken in COVID crash. Entire beta/systematic risk family abandoned. | L1011: -rank(beta_last_60_days_spy)
A1012: M18 | B1012: fscore_quality Naked | C1012: TOP3000 | D1012: 0.01 | E1012: 0 | F1012: 10.3 | G1012: =IFERROR(MAX(Y1012:AA1012),"") -> 0 | H1012: ❌ Rejected | I1012: Coverage Too Low | K1012: Only 19-26 stocks in TOP3000 universe. 30% coverage = ~45 stocks. Statistically meaningless. Do not revisit any fscore variants. | L1012: -rank(fscore_quality)
A1013: M19 | B1013: Systematic Risk 90d Naked | C1013: TOP3000 | D1013: -0.28 | E1013: -0.14 | F1013: 19.03 | G1013: =IFERROR(MAX(Y1013:AA1013),"") -> 0 | H1013: ❌ Rejected | I1013: Dead Signal | K1013: Negative every year. Risk factor family fully exhausted. Do not revisit. | L1013: -rank(systematic_risk_last_90_days)
A1014: O1 | B1014: Forward Price 270d ts_rank | C1014: TOP3000 | D1014: 0.2 | E1014: 0.08 | F1014: 17.38 | H1014: ❌ Rejected | I1014: 2021-2022 Collapse | K1014: 2021 and 2022 both negative. Genuine structural reversal, not COVID spike. ts_rank cannot fix. Options level signals confirmed dead. | L1014: -rank(ts_rank(forward_price_270,252))
A1015: O2 | B1015: Call Breakeven 10d Naked | C1015: TOP3000 | D1015: -0.07 | E1015: -0.02 | F1015: 3.26 | H1015: ❌ Rejected | I1015: Dead Signal | K1015: Negative IS. 2020 spike surrounded by negative years = noise not signal. Entire call_breakeven family dead at all windows. | L1015: -rank(call_breakeven_10)
A1016: O3 | B1016: PCR Volume 270d Naked | C1016: TOP3000 | D1016: -0.51 | E1016: -0.09 | F1016: 64.38 | H1016: ❌ Rejected | I1016: Dead Signal | K1016: Negative IS. 64% TO ceiling. Negative every year except 2022. pcr_vol family dead at all windows. | L1016: -rank(pcr_vol_270)
A1017: O4 | B1017: Historical Vol 180d ts_rank | C1017: TOP3000 | D1017: 0.3 | E1017: 0.11 | F1017: 12.69 | H1017: ❌ Rejected | I1017: Fitness Block | K1017: 2019 negative (-0.57). Weak signal throughout, no year above 0.87. Fitness ceiling. Abandon. | L1017: -rank(ts_rank(historical_volatility_180,252))
A1018: O5 | B1018: PCR Volume 60d Naked | C1018: TOP3000 | D1018: -0.5 | E1018: -0.09 | F1018: 68.18 | H1018: ❌ Rejected | I1018: Dead Signal | K1018: Mirror of O3. 68% TO + negative IS. pcr_vol family confirmed dead at all windows. | L1018: -rank(pcr_vol_60)
A1019: O6 | B1019: Call Breakeven 30d Naked | C1019: TOP3000 | D1019: -0.06 | E1019: -0.01 | F1019: 3.18 | H1019: ❌ Rejected | I1019: Dead Signal | K1019: Near-identical to O2. Entire breakeven family (call and put, all windows) is one dead signal. | L1019: -rank(call_breakeven_30)
A1020: O7 | B1020: Put Breakeven 10d Naked | C1020: TOP3000 | D1020: -0.07 | E1020: -0.02 | F1020: 3.63 | H1020: ❌ Rejected | I1020: Dead Signal | K1020: Same profile as O6/O2. Put and call breakeven share identical broken signal. Family fully exhausted. | L1020: -rank(put_breakeven_10)
A1021: O8 | B1021: IV Put 30d ts_rank | C1021: TOP3000 | D1021: -0.56 | E1021: -0.19 | F1021: 32.01 | H1021: ❌ Rejected | I1021: Dead Signal | K1021: Negative every year except 2021. ts_rank made it worse. IV put family dead in all directions. | L1021: -rank(ts_rank(implied_volatility_put_30,252))
A1022: S1 | B1022: NetRec% ts_rank | C1022: TOP3000 | D1022: 0.65 | E1022: 0.27 | F1022: 3.6 | H1022: ❌ Rejected | I1022: 2021-2022 Collapse | K1022: Test>Train gap. 2019 and 2021 negative. Not COVID spike — structural regime weakness. 5 variants tested, all failed. | L1022: -rank(ts_rank(snt1_d1_netrecpercent,252))
A1023: S1b | B1023: NetRec% Market Neut | C1023: TOP3000 | D1023: 0.65 | E1023: 0.32 | F1023: 2.86 | H1023: ❌ Rejected | I1023: 2021-2022 Collapse | K1023: Market neutralization distorted Long/Short counts. 2021/2022 still negative. Did not fix structural weakness. | L1023: -rank(ts_rank(snt1_d1_netrecpercent,252))
A1024: S1c | B1024: NetRec% A4 Template | C1024: TOP3000 | D1024: 1.21 | E1024: 0.56 | F1024: 24.98 | H1024: ❌ Rejected | I1024: Fitness Block | K1024: Best Sentiment result. Good yearly profile but Fitness 0.56. 25% TO needs ~10.3% returns for Fitness 1.0. Unreachable. | L1024: -rank(ts_decay_linear(ts_rank(snt1_d1_netrecpercent,252),21)*rank(ts_delta(close,5)))
A1025: S1d | B1025: NetRec% Decay0 Hybrid | C1025: TOP3000 | D1025: 1.36 | E1025: 0.53 | F1025: 42.4 | H1025: ❌ Rejected | I1025: Fitness Block | K1025: Best yearly profile in Sentiment family. 2021 flat not negative. 42% TO kills Fitness — need 17% returns at this Sharpe for Fitness 1.0. | L1025: -rank(ts_decay_linear(ts_rank(snt1_d1_netrecpercent,252),4)*rank(ts_delta(close,5)))
... A1043: DV15 | B1043: Indicated Dividend Yield ts_rank | C1043: TOP3000 | D1043: 0.53 | E1043: 0.25 | F1043: 8.02 | H1043: ❌ Rejected | I1043: Fitness Below Threshold | K1043: Dead. | L1043: -rank(ts_rank(mdl177_2_deepvaluefactor_indidivy,252))
A1044: DV16 | B1044: Price/Dividend Yield 126w ts_rank | C1044: TOP3000 | D1044: 1.61 | E1044: 1.26 | F1044: 13.15 | G1044: 0.6729 | J1044: 05/09/2026 | K1044: IS 1.61, Fit 1.26. All 5 years positive. Max corr 0.6729 vs DV2c. 126w window discovered via pdy borderline test. | L1044: -rank(ts_rank(mdl177_2_deepvaluefactor_pdy,126))
A1045: NEW-2 | B1045: 5yr RelValue TOP500 ts_rank | C1045: TOP500 | D1045: 1.89 | E1045: 1.88 | F1045: 12.45 | G1045: 0.6458 | K1045: IS 1.89, Fit 1.88. TOP500 universe variant of M11. Max corr 0.6458 vs M11. Best fitness in batch. | L1045: -rank(ts_rank(mdl177_2_5yearrelativevaluefactor_rel5yfwdep,252))
A1046: NEW-3 | B1046: TTM OCF/EV TOP500 ts_rank | C1046: TOP500 | D1046: 1.77 | E1046: 1.62 | F1046: 10.92 | G1046: 0.5456 | K1046: IS 1.77, Fit 1.62. TOP500 variant of M6. Max corr 0.5456 vs M6. | L1046: -rank(ts_rank(mdl177_2_sensitivityfactor400_ttmocfev,252))
A1047: NEW-4 | B1047: TTM OCF/EV TOP1000 ts_rank | C1047: TOP1000 | D1047: 1.66 | E1047: 1.36 | F1047: 10.24 | G1047: 0.7339 | H1047: ❌ Rejected | I1047: Self-Correlation | K1047: IS 1.66, Fit 1.36. Corr 0.7339 vs M6 — over threshold. Rejected. | L1047: -rank(ts_rank(mdl177_2_sensitivityfactor400_ttmocfev,252))
A1048: NEW-5 | B1048: TTM FCF/Price TOP500 ts_rank | C1048: TOP500 | D1048: 1.8 | E1048: 1.58 | F1048: 10.17 | G1048: 0.2826 | K1048: IS 1.80, Fit 1.58. TOP500 variant of DV5. Max corr 0.2826 vs M6 — very clean. | L1048: -rank(ts_rank(mdl177_2_deepvaluefactor_ttmfcfp,252))
A1049: NEW-6 | B1049: TTM FCF/Price TOP1000 ts_rank | C1049: TOP1000 | D1049: 1.46 | E1049: 1 | F1049: 9.26 | G1049: 0.4608 | K1049: IS 1.46, Fit 1.00. TOP1000 variant of DV5. Max corr 0.4608 vs M6. Check yearly before submitting. | L1049: -rank(ts_rank(mdl177_2_deepvaluefactor_ttmfcfp,252))
A1050: NEW-7 | B1050: PDY 126w TOP500 ts_rank | C1050: TOP500 | D1050: 1.6 | E1050: 1.19 | F1050: 14.99 | G1050: 0.4271 | K1050: IS 1.60, Fit 1.19. TOP500 variant of DV16. Max corr 0.4271 vs DV2c. | L1050: -rank(ts_rank(mdl177_2_deepvaluefactor_pdy,126))
A1051: NEW-1 | B1051: 5yr RelValue TOP1000 ts_rank | C1051: TOP1000 | D1051: 1.92 | E1051: 1.75 | F1051: 11.9 | G1051: 0.7994 | H1051: ❌ Rejected | I1051: Self-Correlation | K1051: IS 1.92, Fit 1.75. Corr 0.7994 vs M11 — just over 0.70. Rejected. TOP500 passed instead. | L1051: -rank(ts_rank(mdl177_2_5yearrelativevaluefactor_rel5yfwdep,252))
A1052: NEW-8 | B1052: NEY TOP1000 ts_rank | C1052: TOP1000 | D1052: 1.35 | E1052: 1.1 | F1052: 11.48 | G1052: 0.8687 | H1052: ❌ Rejected | I1052: Self-Correlation | K1052: IS 1.35, Fit 1.10. Corr 0.8687 vs M15b — same signal. | L1052: -rank(ts_rank(mdl177_2_sensitivityfactor400_ney,252))
A1053: NEW-9 | B1053: NEY TOP500 ts_rank | C1053: TOP500 | D1053: 1.33 | E1053: 1.07 | F1053: 12.17 | G1053: 0.649 | K1053: IS 1.33, Fit 1.07. TOP500 variant of M15b. Max corr 0.6490 vs M15b. Check yearly before submitting. | L1053: -rank(ts_rank(mdl177_2_sensitivityfactor400_ney,252))
A1054: GA-1 | B1054: GARP capeff × Momentum (mdl177_2) | C1054: TOP3000 | D1054: 1.81 | E1054: 1.47 | F1054: 14.8 | G1054: 0.8411 | H1054: ❌ Rejected | I1054: Self-Correlation | K1054: IS 1.81, Fit 1.47. Corr 0.8411 vs DV2c. Score change -107 — hurts book. Permanently rejected. | L1054: -rank(ts_rank(mdl177_2_garpanalystmodel_qgp_capeff,252)*rank(ts_delta(close,21)))
A1055: GA-2 | B1055: GARP capeff × Momentum (mdl177) | C1055: TOP3000 | D1055: 1.86 | E1055: 1.56 | F1055: 14.42 | K1055: IS 1.86, Fit 1.56. Corr not yet checked — likely same issue as GA-1. Check before submitting. | L1055: -rank(ts_rank(mdl177_garpanalystmodel_qgp_capeff,252)*rank(ts_delta(close,21)))
A1056: GA-3 | B1056: GARP capeff Naked (mdl177) | C1056: TOP3000 | D1056: 1.74 | E1056: 1.42 | F1056: 9.86 | K1056: IS 1.74, Fit 1.42. Corr not yet checked. Check before submitting. | L1056: -rank(ts_rank(mdl177_garpanalystmodel_qgp_capeff,252))
A1057: GA-4 | B1057: GARP capeff Naked (mdl177_2) | C1057: TOP3000 | D1057: 1.57 | E1057: 1.19 | F1057: 10.79 | K1057: IS 1.57, Fit 1.19. Corr not yet checked. Likely correlated with GA-1 rejected variant. | L1057: -rank(ts_rank(mdl177_2_garpanalystmodel_qgp_capeff,252))
A1058: GA-5 | B1058: GARP roefcf × Momentum (mdl177) | C1058: TOP3000 | D1058: 1.59 | E1058: 1.22 | F1058: 13.3 | K1058: IS 1.59, Fit 1.22. Corr not yet checked. | L1058: -rank(ts_rank(mdl177_garpanalystmodel_qgp_roefcf,252)*rank(ts_delta(close,21)))
A1059: RV-1 | B1059: RelValue ttmfcfp × Momentum (mdl177_2) | C1059: TOP3000 | D1059: 1.9 | E1059: 1.58 | F1059: 12.93 | H1059: ❌ Rejected | I1059: Score +66 only — superseded by RV-1b duplicate; submit RV-1b link instead | K1059: IS 1.90, Fit 1.58. Same variable family as DV5 — check corr before submitting. | L1059: -rank(ts_rank(mdl177_2_relativevaluemodel_ttmfcfp,252)*rank(ts_delta(close,21)))
A1060: RV-2 | B1060: RelValue ttmfcfp Naked (mdl177_2) | C1060: TOP3000 | D1060: 1.66 | E1060: 1.19 | F1060: 8.22 | H1060: ❌ Rejected | I1060: Corr 0.9617 vs DV5 — too high | K1060: IS 1.66, Fit 1.19. Same variable family as DV5 — check corr. | L1060: -rank(ts_rank(mdl177_2_relativevaluemodel_ttmfcfp,252))
A1061: RV-3 | B1061: RelValue ttmfcfp × Momentum (mdl177) | C1061: TOP3000 | D1061: 1.9 | E1061: 1.58 | F1061: 12.93 | K1061: IS 1.90, Fit 1.58. Alt prefix of RV-1 — likely same signal. | Score +66, corr 0.4903 — same as RV-1, use this link | L1061: -rank(ts_rank(mdl177_relativevaluemodel_ttmfcfp,252)*rank(ts_delta(close,21)))
A1062: RV-4 | B1062: RelValue ttmfcfp Naked (mdl177) | C1062: TOP3000 | D1062: 1.66 | E1062: 1.19 | F1062: 8.22 | H1062: ❌ Rejected | I1062: Corr 0.9617 vs DV5 — too high (naked version) | K1062: IS 1.66, Fit 1.19. Alt prefix of RV-2 — likely same signal. | L1062: -rank(ts_rank(mdl177_relativevaluemodel_ttmfcfp,252))
A1063: FA-1 | B1063: FA fwd EP × Momentum | C1063: TOP3000 | D1063: 1.4 | E1063: 1.06 | F1063: 14.26 | H1063: ❌ Rejected | I1063: Corr 1.0000 vs DV2c — literally identical alpha | K1063: IS 1.40, Fit 1.06. Similar to DV2c — check corr before submitting. | L1063: -rank(ts_rank(mdl177_fa_fc_fwdep,252)*rank(ts_delta(close,21)))
...

Sheet WQ_Brain_Tracker_Session20
A1: Field | B1: Description | C1: Category | D1: Status | E1: Signal Strength | F1: Notes
A2: close | B2: Daily closing price | C2: Price-Volume | D2: ✅ In Use | E2: Strong | F2: Foundation of all PV signals. 60% TO ceiling as primary.
A3: volume | B3: Daily trading volume | C3: Price-Volume | D3: ✅ In Use | E3: Strong | F3: Use as ts_rank for robustness. High TO when primary.
A4: returns | B4: Daily returns | C4: Price-Volume | D4: ✅ In Use | E4: Strong | F4: Used in vol calculations and momentum signals.
A5: high | B5: Daily high price | C5: Price-Volume | D5: ✅ In Use | E5: Strong | F5: Used in CLV and range calculations.
A6: low | B6: Daily low price | C6: Price-Volume | D6: ✅ In Use | E6: Strong | F6: Used in CLV and range calculations.
A7: open | B7: Daily open price | C7: Price-Volume
A8: vwap | B8: Volume-weighted average price | C8: Price-Volume | D8: ⚪ Backlog | E8: Weak | F8: 60% TO ceiling blocks Fitness. Signal exists.
A9: adv20 | B9: Average daily volume over 20 days | C9: Price-Volume | D9: ⚪ Backlog | E9: Weak | F9: Better as normalizer than primary signal. 85% TO as primary.
A10: current_ratio | B10: Current Ratio | C10: Fundamental | D10: ✅ In Use | E10: Strong | F10: Liquidity-based. Works because not COVID-distorted. Delay 1 only.
A11: sales_ps | B11: Sales per Share (Quarterly) | C11: Fundamental | D11: ✅ In Use | E11: Strong | F11: Template alpha. Best fundamental found. No COVID distortion.
A12: scl12_buzz | B12: relative sentiment volume | C12: Social Media | D12: ❌ Abandoned | E12: Weak | F12: A26 family abandoned. 3 fix variants all failed. Fitness ceiling 0.56.
A13: snt_buzz | B13: Negative relative sentiment volume measure for current day, with missing values filled as 0 | C13: Social Media | D13: ❌ Abandoned | E13: Dead | F13: Signal inverted. 10+ variants tested. IS Fitness ceiling 0.98. Permanently exhausted. Do not revisit.
A14: snt_buzz_bfl | B14: Negative relative sentiment volume measure for current day, with missing values filled as 1 | C14: Social Media | D14: ❌ Abandoned | E14: Dead | F14: Negative IS Sharpe in all variants. Dead signal.
A15: scl12_sentiment | B15: sentiment | C15: Social Media | D15: ❌ Abandoned | E15: Dead | F15: 86% TO creates mathematical Fitness ceiling. IS Fitness 0.08 naked. Abandoned Session 11.
A16: snt_value | B16: Negative sentiment score/indicator for current day, with missing values filled as 0 | C16: Social Media | D16: ❌ Abandoned | E16: Dead | F16: Confirmed dead (negative Sharpe both signs). Previously listed as Z3 — reclassified to Z5 (skip if quota is limited). Do not re-queue.
A17: snt1_d1_stockrank | B17: Rank (0-100) based on equity-style factors, where higher values reflect a stronger buy signal and lower values a sell signal | C17: Sentiment / Analyst | D17: ❌ Abandoned | E17: Dead | F17: Two-test exhausted: naked failed 2021/2022, A4 template also failed. Abandoned Session 11.
A18: implied_volatility_call_60 | B18: Implied volatility of the at-the-money call for the stock with an expiration 60 calendar days from the measurement date | C18: Options - Volatility | D18: 🟠 Test Soon | E18: Medium | F18: IV filter confirmed at >0.3. Need new uncorrelated inner signal.
A19: snt_social_value | B19: Z-score of sentiment | C19: Social Media | D19: ❌ Abandoned | E19: Dead | F19: Negative both signs. Abandoned Session 11.
A20: snt_social_volume | B20: Normalized tweet volume | C20: Social Media | D20: ❌ Abandoned | E20: Dead | F20: Duplicate result with snt_value confirmed dead. Abandoned Session 11.
A21: scl12_buzzvec | B21: Vector representing the volume of social media sentiment/mentions related to the instrument | C21: Social Media
A22: snt_buzz_ret | B22: negative return of relative sentiment volume | C22: Social Media | D22: ❌ Abandoned | E22: Dead | F22: Negative both signs. Abandoned Session 11.
A23: scl12_sentvec | B23: Vector representing the sentiment score (bullish/bearish/neutral) derived from social media data for the instrument | C23: Social Media
A24: scl12_typevec | B24: Vector containing the type indices identifying the categories of instruments in the dataset | C24: Social Media
A25: scl12_alltype_buzzvec | B25: sentiment volume | C25: Social Media
A26: snt_value_fast_d1 | B26: Negative sentiment score/indicator for current day, with missing values filled as 0 | C26: Social Media
A27: snt_buzz_fast_d1 | B27: Negative relative sentiment volume measure for current day, with missing values filled as 0 | C27: Social Media
A28: scl12_sentiment_fast_d1 | B28: sentiment | C28: Social Media
A29: scl12_buzz_fast_d1 | B29: relative sentiment volume | C29: Social Media
A30: snt_buzz_bfl_fast_d1 | B30: Negative relative sentiment volume measure for current day, with missing values filled as 1 | C30: Social Media
A31: scl12_alltype_sentvec | B31: sentiment | C31: Social Media
A32: scl12_alltype_typevec | B32: instrument type index | C32: Social Media
A33: snt_buzz_ret_fast_d1 | B33: negative return of relative sentiment volume | C33: Social Media
A34: snt1_d1_analystcoverage | B34: Number of analysts providing an earnings estimate for the stock | C34: Sentiment / Analyst
... A1064: fnd6_newqeventv110_pncwippq | B1064: Core Pension w/o Interest Adjustment Pretax Preliminary | C1064: Fundamental
A1065: pcr_vol_10 | B1065: Ratio of total put option volume to call option volume for options expiring in 10 days, reflecting very short-term sentiment flow | C1065: Options - Analytics | D1065: 🔴 Abandon | E1065: Dead | F1065: Put-call ratio tested — no meaningful signal found.
A1066: enterprise_value | B1066: Enterprise Value | C1066: Fundamental | D1066: 🔴 Abandon | E1066: Weak | F1066: COVID killed EV/EBITDA relationship. 2021+2022 both negative.
A1067: debt | B1067: Debt | C1067: Fundamental | D1067: 🔴 Abandon | E1067: Dead | F1067: COVID stimulus inverted all leverage signals. Never use.
A1068: ebit | B1068: Earnings Before Interest and Taxes | C1068: Fundamental | D1068: 🔴 Abandon | E1068: Dead | F1068: Negative IS. External PDF Sharpe unverifiable.
A1069: bookvalue_ps | B1069: Book Value Per Share | C1069: Fundamental | D1069: 🔴 Abandon | E1069: Weak | F1069: Distorted by share buybacks. Weaker than sales_ps.
A1070: return_assets | B1070: Return on Assets | C1070: Fundamental | D1070: 🔴 Abandon | E1070: Dead | F1070: COVID-distorted. Negative IS Sharpe.
A1071: mdl177_garpanalystmodel_qgp_vfpriceratio | B1071: Value to Price Rank — intrinsic valuation vs market price | C1071: Model | D1071: ✅ In Use | E1071: Strong | F1071: ts_rank(252) version submitted as Alpha 11 (MC3). IS Fitness 1.66, IS Sharpe 1.89. All years positive except 2023 slight dip. Near-zero corr with portfolio.
A1072: mdl177_2_sensitivityfactor400_ttmocfev | B1072: Trailing 12-month operating cash flow per share / enterprise value per share | C1072: Model | D1072: ✅ In Use | E1072: Strong | F1072: ts_rank(252) version submitted as Alpha 12 (M6). IS Fitness 1.22, IS Sharpe 1.72. All 5 years positive — most consistent yearly profile in tracker.
A1073: mdl177_2_5yearrelativevaluefactor_rel5yfwdep | B1073: 5-year Relative Leading 12-Month Earnings Yield: next 4-quarter consensus analyst earnings-to-price ratio minus the 60-month average, scaled by the standard deviation | C1073: Model - Analyst
A1074: mdl177_fangma_gpam_usa_fangma_gpam11 | B1074: A composite or specialized metric summarizing growth or profitability characteristics for a group of prominent technology firms. | C1074: Model - Analyst
A1075: mdl177_2_garpanalystmodel_qgp_capeff | B1075: Measurement of how efficiently a company utilizes its capital/resources, ranked relative to peers | C1075: Model - Analyst | D1075: 🔴 Abandon | E1075: Toxic | F1075: IS 1.81. Corr 0.84 vs DV2c. Score -107. Permanently rejected.
A1076: mdl177_fangma_rvm_usa_fangma_rvm6 | B1076: Relative value model 6 for FANGMA (Facebook, Apple, Netflix, Google, Microsoft, Amazon) | C1076: Model - Analyst
A1077: mdl177_2_earningsqualityfactor_uap | B1077: Difference between current accounts payable and expected level (prior year's balance multiplied by COGS growth in trailing 12 months), scaled by total assets | C1077: Model - Analyst
A1078: mdl177_2_sensitivityfactor400_chg12msip | B1078: Change in the short interest ratio (shares sold short / shares outstanding) over the previous 12 months | C1078: Model - Analyst | D1078: 🔴 Abandon | E1078: Dead | F1078: IS -1.0. Dead.
A1079: mdl177_2_liquidityriskfactor_si_ratio | B1079: Ratio of shares sold short to average daily trading volume over the last 30 days | C1079: Model - Analyst
A1080: mdl177_2_garpanalystmodel_qgp_vfpriceratio | B1080: Ranking based on the ratio of intrinsic (fundamental, value-based) valuation to market price, indicating relative under/overvaluation | C1080: Model - Analyst
A1081: mdl177_2_sensitivityfactor400_ney | B1081: Normalized Earnings Yield: It is defined as the average of three normalized earnings calculated by ROE, NPM and EPS FY2, scaled by price. | C1081: Model - Analyst
A1082: mdl177_earningsqualityfactor_uap | B1082: Unexpected change in accounts payable, difference between current and expected accounts payable scaled by total assets | C1082: Model - Analyst
A1083: mdl177_2_sensitivityfactor400_rev3my2std | B1083: 3-M Revision in FY2 EPS Forecasts: Dispersion Relative: It is defined as the change in a stock's current analysts mean earnings estimate for fiscal year 2 less that of three months ago, scaled by the standard deviation of analyst forecasts as of three months ago. | C1083: Model - Analyst | D1083: 🔴 Abandon | E1083: Dead | F1083: IS -0.6. Dead.
A1084: mdl177_2_deepvaluefactor_curep | B1084: Current Earnings Yield (sum of recent 3 quarters EPS and analyst estimates, divided by price) | C1084: Model - Analyst
A1085: mdl177_liquidityriskfactor_si_ratio_alt | B1085: Short interest ratio: shares sold short divided by average daily volume over last 30 days; estimates days to cover shorts | C1085: Model - Analyst | D1085: 🔴 Abandon | E1085: Dead | F1085: IS -0.74. Dead.
A1086: mdl177_valueanalystmodel_qva_chgacc_alt | B1086: Rank of change in net operating working capital for a stock compared to peers | C1086: Model - Analyst
A1087: mdl177_2_managementqualityfactor_saleicap | B1087: Trailing 12-month sales divided by invested capital | C1087: Model - Analyst | D1087: 🔴 Abandon | E1087: Dead | F1087: IS 0.79. Dead. Full family abandoned.
A1088: mdl177_2_deepvaluefactor_fcfp | B1088: Leading 12-Month Median Earnings Yield | C1088: Model - Analyst
A1089: mdl177_2_managementqualityfactor_noato | B1089: Net operating asset turnover: trailing 12-month sales divided by 4-quarters average net operating assets (short-term debt + long-term debt + preferred equity + common equity - cash) | C1089: Model - Analyst | D1089: 🔴 Abandon | E1089: Dead | F1089: IS 0.29. Dead.
A1090: mdl177_deepvaluefactor_curep_alt | B1090: Cash-to-Price | C1090: Model - Analyst
A1091: mdl177_valueanalystmodel_qva_chgacc | B1091: Rank of change in net operating working capital for the stock | C1091: Model - Analyst
A1092: mdl177_garpanalystmodel_qgp_capeff | B1092: Measurement of capital utilization efficiency, showing how effectively the company uses its capital for growth/profit | C1092: Model - Analyst | D1092: 🔴 Abandon | E1092: Toxic | F1092: IS 1.86. Same corr issue. Reject all capeff variants.
A1093: mdl177_2_valueanalystmodel_qva_chgacc | B1093: Rank based on change in net operating working capital, reflecting shifts in operational liquidity or efficiency | C1093: Model - Analyst
A1094: mdl177_garpanalystmodel_qgp_relgrowth | B1094: Rank comparing company's growth metrics against its industry peers, showing relative growth strength | C1094: Model - Analyst | D1094: ❌ Abandoned | E1094: Dead | F1094: IS 0.98, Fit 0.61. Dead.
A1095: mdl177_5shortsentimentfactor_act_util | B1095: Actual Utilization Rate: the real observed proportion of shares lent out (actively used for short selling) versus available supply | C1095: Model - Analyst | D1095: 🔴 Abandon | E1095: Dead | F1095: IS 0.03. Dead.
A1096: mdl177_2_sensitivityfactor400_chginvavgast | B1096: 12-month change in quarterly total inventory, normalized by the average assets between the most recent quarter-end and the same quarter one year prior | C1096: Model - Analyst | D1096: 🔴 Abandon | E1096: Dead | F1096: IS 0.36. Dead.
A1097: mdl177_fa_app | B1097: Average Payable Period: Average time (in days) taken to pay suppliers, calculated as trailing 12-month accounts payable times 365 divided by the trailing 12-month cost of goods sold | C1097: Model - Analyst
A1098: mdl177_2_relativevaluemodel_ttmfcfp | B1098: TTM Free Cash Flow-to-Price; trailing 12-month free cash flow per share divided by month-end trading price. Free cash flow is operating cash flow minus capital expenditures and cash dividends | C1098: Model - Analyst | D1098: 🟠 Test Soon | E1098: Strong | F1098: IS 1.90, Fit 1.58. Corr check pending — same var as DV5. High priority.
A1099: mdl177_2_sensitivityfactor400_chgqtrepssurp | B1099: Change in Real Earnings Surprise : It is defined as the change in quarterly earnings surprise (Actual EPS - Consensus Estimate EPS), scaled by the most recent closing price. | C1099: Model - Analyst | D1099: 🔴 Abandon | E1099: Dead | F1099: IS -0.59. Dead.
A1100: mdl177_relativevaluemodel_ttmfcfp | B1100: Trailing Twelve Month Free Cash Flow-to-Price; trailing 12-month free cash flow per share divided by month-end trading price | C1100: Model - Analyst | D1100: 🟠 Test Soon | E1100: Strong | F1100: IS 1.90, Fit 1.58. Alt prefix. Likely same as mdl177_2 version.
A1101: mdl177_2_vma2_vma2_va | B1101: Value Analyst II composite score aggregating valuation-oriented subscores (Earnings Quality, Earnings Valuation, Financial Statement Valuation, Investor Sentiment) | C1101: Model - Analyst | D1101: ✅ In Use | E1101: Strong | F1101: IS 1.78. VMA-2 submitted +141. VMA-1 (momentum) pending corr check.
A1102: mdl177_fa_fc_fwdep | B1102: Leading 12-Month Mean Earnings Yield: Next 4-quarter mean consensus earnings estimate divided by trading price | C1102: Model - Analyst | D1102: 🟠 Test Soon | E1102: Medium | F1102: IS 1.40, Fit 1.06 (FA-1). Corr check pending — similar to DV2c.
A1103: mdl177_2_sensitivityfactor400_earnshortfall | B1103: Earnings Shortfall : It is defined as the difference between reported accounting earnings and free cash flow, scaled by average assets. | C1103: Model - Analyst | D1103: 🔴 Abandon | E1103: Dead | F1103: IS 0.72. Dead.
A1104: mdl177_5shortsentimentfactor_dmd_conc | B1104: Demand value concentration: degree to which borrowing demand is concentrated among a few borrowers | C1104: Model - Analyst | D1104: 🔴 Abandon | E1104: Dead | F1104: IS 0.49. Dead.
A1105: mdl177_deepvaluefactor_fcfp_alt | B1105: Leading 12-Month Median Earnings Yield | C1105: Model - Analyst
A1106: mdl177_v1_400_yoychgda | B1106: Year-over-year change in leverage: difference between most recent quarterly total liabilities as a percentage of total assets and the same percentage one year ago | C1106: Model - Analyst | D1106: 🔴 Abandon | E1106: Dead | F1106: IS 0.39. Dead.
A1107: mdl177_2_deepvaluefactor_estep | B1107: Forward 12-month median earnings-to-price (earnings yield) | C1107: Model - Analyst
A1108: mdl177_2_managementqualityfactor_app | B1108: Average payable period: average trailing 12-month accounts payable times 365 divided by trailing 12-month cost of goods sold | C1108: Model - Analyst
A1109: mdl177_2_earningmomentumfactor400_q1aepsg | B1109: EPS growth estimate for next fiscal quarter | C1109: Model - Analyst | D1109: ❌ Abandoned | E1109: Weak | F1109: IS 1.27, Fit 0.86. Just below threshold. Low priority.
A1110: mdl177_2_deepvaluefactor_pdy | B1110: Indicated dividend yield | C1110: Model - Analyst
A1111: mdl177_5shortsentimentfactor_dmd_supply | B1111: Demand-to-supply ratio in securities lending, indicating borrow demand relative to lendable supply | C1111: Model - Analyst | D1111: 🔴 Abandon | E1111: Dead | F1111: IS 0.13. Dead.
A1112: mdl177_valanalystmodel_qva_chgacc | B1112: Change in Net Op Working Capital Rank | C1112: Model - Analyst
A1113: mdl177_2_sensitivityfactor400_pbroeresidual | B1113: Adjusted price-to-book signal incorporating firm growth, based on Wilcox and Philips (2005), representing the residual from combining price-to-book and return-on-equity | C1113: Model - Analyst
A1114: mdl177_fa_fc_fcfp | B1114: Forward Free Cash Flow-to-Price: Next 4-quarter mean consensus earnings estimate plus trailing 12-month depreciation expense per share minus capital expenditures, divided by trading price | C1114: Model - Analyst | D1114: ❌ Abandoned | E1114: Weak | F1114: IS 0.99, Fit 0.58. Dead.
A1115: mdl177_garpanalystmodel_qgp_roefcf | B1115: Combined measure of profitability (ROE) and cash flow (FCF), ranking stocks by both financial quality factors | C1115: Model - Analyst | D1115: 🟠 Test Soon | E1115: Medium | F1115: IS 1.59, Fit 1.22 — passed. Corr check pending before submit.
A1116: mdl177_2_valueanalystmodel_qva_composite | B1116: Composite rank combining multiple value analyst measures for overall scoring | C1116: Model - Analyst
A1117: mdl177_historicalgrowthfactor_chgnpm_alt | B1117: Most recent quarterly net profit margin minus net profit margin from four quarters ago | C1117: Model - Analyst | D1117: 🔴 Abandon | E1117: Dead | F1117: IS 1.11, Fit 0.70. Dead.
A1118: mdl177_2_sensitivityfactor400_rev3my1std | B1118: The change in a stock's current analysts mean earnings estimate for fiscal year 1 less that of three months ago, scaled by the standard deviation of analyst forecasts as of three months ago. | C1118: Model - Analyst | D1118: 🔴 Abandon | E1118: Dead | F1118: IS 0.02. Dead.
A1119: mdl177_2_managementqualityfactor_ollev | B1119: Operating liability leverage: 1 minus the ratio of (short-term debt + long-term debt + common equity + preferred equity - cash) to (total assets - cash) in the current quarter | C1119: Model - Analyst | D1119: 🔴 Abandon | E1119: Dead | F1119: IS -0.03. Dead.
A1120: mdl177_earningsqualityfactor_ttmaccu_alt | B1120: Trailing twelve months accruals (earnings quality measure based on accruals) | C1120: Model - Analyst
A1121: mdl177_fa_aspanratio | B1121: Attention Span Ratio | C1121: Model - Analyst | D1121: 🔴 Abandon | E1121: Dead | F1121: IS 0.65. Dead.
A1122: mdl177_2_deepvaluefactor_fwdep | B1122: Forward 12-month earnings-to-price ratio (mean consensus EPS divided by trading price) | C1122: Model - Analyst
A1123: mdl177_deepvaluefactor_fwdep_alt | B1123: Forward 12-month Earnings-to-Price: next four quarters' mean consensus EPS divided by price | C1123: Model - Analyst
A1124: mdl177_2_surpriseanalystmodel_qsa_surpsn | B1124: Rank of a company's earnings or revenue surprise, normalized relative to its sector (sector-neutral surprise analyst rank) | C1124: Model - Analyst | D1124: 🔴 Abandon | E1124: Dead | F1124: IS 0.24. Dead.
A1125: mdl177_deepvaluefactor_estep_alt | B1125: TTM EBITDA-to-Price | C1125: Model - Analyst
A1126: mdl177_surpriseanalystmodel_qsa_surpsn | B1126: Surprise Analyst Sector-Neutral Rank | C1126: Model - Analyst | D1126: 🔴 Abandon | E1126: Dead | F1126: IS 0.24. Dead.
A1127: mdl177_2_sensitivityfactor400_y2aepsgpc | B1127: Percentage change in consensus analyst EPS forecast from fiscal year 1 to fiscal year 2, normalized by year 1 forecast (forward growth rate) | C1127: Model - Analyst | D1127: 🔴 Abandon | E1127: Dead | F1127: IS -0.71. Dead.
A1128: mdl177_2_pricemomentumfactor_indrelrtn5d | B1128: Stock's 5-day return minus industry average 5-day return, scaled by industry standard deviation, reflecting industry-relative momentum | C1128: Model - Analyst
A1129: mdl177_2_sensitivityfactor400_chg12mtotdebt | B1129: Relative change in total debt (sum of long-term and short-term debt) over the past 12 months | C1129: Model - Analyst | D1129: 🔴 Abandon | E1129: Dead | F1129: IS -0.21. Dead.
...

Sheet 📈 Dashboard
A1: 🧠 WorldQuant BRAIN — Research Dashboard
A3: 🏆 IQC 2026 Status
A4: D1 Score | B4: 8526 | C4: Total Tested | D4: =COUNTA('📊 Results'!A:A)-1 -> 164
A5: IQC Stage 1 Rank | C5: ✅ Submitted | D5: =COUNTIF('📊 Results'!H:H,"✅ Submitted") -> 13
A6: Challenge Score | B6: 13851 | C6: ❌ Rejected | D6: =COUNTIF('📊 Results'!H:H,"❌ Rejected") -> 121
A7: Challenge Rank | B7: 8017 | C7: Best Sharpe | D7: =MAX('📊 Results'!D:D) -> 2.1
A8: Deadline | B8: May 18, 2026 | C8: Best Fitness | D8: =MAX('📊 Results'!E:E) -> 1.88
A9: Days Remaining | B9: =DATE(2026,5,19)-TODAY() -> 5 | C9: Fields Tracked | D9: =COUNTA(WQ_Brain_Tracker_Session20!A:A)-1 -> 1731
A11: 📋 Submit Queue (highest score first)
A12: Date | B12: Alpha | C12: Score Δ | D12: Description
A13: ✅ May 9 | B13: NEW-5b | C13: +552 | D13: TOP500 DV5 — DONE
A14: ✅ May 9/10 | B14: VA-1 | C14: +238 | D14: TOP3000 valanalystmodel_qva_incstmt — DONE
A15: ✅ May 10 | B15: NEW-3b | C15: +340 | D15: TOP500 ttmocfev naked — DONE
A16: ✅ May 12 | B16: ZY2OXdKQ 🆕 | C16: +238 | D16: TOP500 rel5ybp — agent find, corr 0.55 — DONE
A17: ✅ May 13 | B17: npnMdNNz 🆕 | C17: +396 | D17: TOP3000 FANGMA VMM11 ts_zscore — DONE
A18: May 14 | B18: 9q90GOld 🔥 | C18: +639 | D18: 🔥 BEST SCORE EVER — TOP200 FANGMA VMM11 ts_rank, corr 0.24. Submit immediately.
A19: May 15 | B19: e7nobL6O 🆕 | C19: TBC | D19: TOP3000 FANGMA VMM11 ts_rank — corr 0.54. Check score on platform first.
A20: May 16 | B20: E5qJ5qr0 🆕 | C20: TBC | D20: TOP3000 days_to_cover ts_rank — corr 0.36. Check score on platform first.
A21: May 17 | B21: MPKN7bXr 🆕 | C21: +37 | D21: TOP500 pdy — fallback. Swap if d1v10 finds better.
A22: ⚠️ Benched | B22: VMA-2 +66, T5K-2 +67, RV-1b +66, NEW-9b +50, Alt-1 +27, DV3b +4 | D22: No slots — use only if queue alpha scores negative
A23: ❌ Dead | B23: T1K-3 corr 0.72 | T5K-4 Fit 0.91 | NEW-7b score -8 | T5K-5 score -304 | onloan_conc sharpe -0.29 | sht_int sharpe 0.54 | D23: All confirmed dead
A27: ⚡ Key Rules
A28: Submit order | B28: Descending score change — NOT IS Sharpe order
A29: Score change | B29: Positive = submit | Negative = reject permanently
A30: Corr threshold | B30: Max self-corr < 0.70 vs all submitted alphas
A31: Fitness floor | B31: ≥ 1.00 (Sharpe ≥ 1.25, TO 1–70%, passed ≥ 6/7)
A32: Variable names | B32: Always verify from Fields Tracker — never guess
A33: TOP500 universe | B33: Usually corr 0.28–0.65 vs TOP3000 — test after any TOP3000 pass
A34: TOP1000 universe | B34: Usually corr 0.73–0.83 — skip unless variable is very different
A35: mdl177_2 prefix | B35: Same family as mdl177 — corr 0.90+ — not an independent signal
A37: 🔬 Research Backlog (Next Session)
A38: Priority | B38: Family | C38: Fields to Test | D38: Rationale
A39: 1 — Running | B39: ❌ DEAD — industryrrelativevaluefactor (double-r) | C39: ALL 8 fields tested — ALL fitness < 1.00. Entire family dead. | D39: d1v10 complete. Every field below fitness threshold. Do not retest.
A40: 2 — Pending | B40: ✅ DONE — fangma_vmm11 tune variants | C40: npnMdNNz (zscore +396), 9q90GOld (ts_rank TOP200 +639), e7nobL6O (ts_rank TOP3000 TBC) | D40: Tune complete. 9q90GOld is best score ever found (+639).
A41: 1 — In d1v11 | B41: valanalystmodel siblings | C41: qva_fwdep, qva_bp, qva_revs, qva_divy, qva_epssurp, qva_valuation | D41: VA-1 scored +238 — siblings in d1v11 batch
A42: 2 — In d1v11 | B42: vma2 siblings | C42: vma2_ma, vma2_ma_ee, vma2_ma_em, vma2_ma_pm | D42: VMA-2 scored +66 — siblings in d1v11 batch
A43: 3 — In d1v11 | B43: 5yr relativevalue siblings | C43: rel5yep, rel5yocfp, rel5yfcfp, rel5ysp, rel5ycoreepsp | D43: rel5ybp +238, rel5yfwdep +385 — more siblings in d1v11
A44: 🔥 HOT — In d1v11 | B44: fangma siblings (gpam/rvm/mam/emf/dvm) | C44: gpam11/10/5, rvm6/1, mam16/11/6/5, emf25/20/15/4, dvm4/1 | D44: vmm11 gave +396/+639 — siblings completely untested. Highest priority.
A45: 4 — In d1v11 | B45: valueanalystmodel (≠ valanalystmodel) | C45: qva_incstmt, qva_finstmt, qva_epmodule, qva_pegy, qva_earnval | D45: DIFFERENT model from valanalystmodel — mdl177_valueanalystmodel prefix. Untested.
A46: 5 — In d1v11 | B46: earningmomentumfactor400 | C46: rev6, numrevy1, numrevq1, epsrm, fqsurs_std, salesurp, stockrating, y1aepsg, cvfy1eps, fcfroey1p | D46: Fresh analyst momentum family — completely untested. 10 candidates.
A47: 🔄 d1v11 STATUS | B47: ~120 expressions queued — run: cp parameters_d1_v11.py parameters.py && python3 main.py | C47: ~180 min runtime | D47: Awaiting results. Run agent.py on CSV when done.
A49: 🧮 Fitness Formula Reference
A50: Formula | B50: Fitness = √( |Returns%| / max(TO%, 12.5%) ) × Sharpe
A51: TO 10% | B51: Need Returns > 6.5% with Sharpe ≥ 1.25
A52: TO 25% | B52: Need Returns > 7% with Sharpe ≥ 1.7
A53: TO 30% | B53: Need Returns > 9% with Sharpe ≥ 1.7
A54: ⚠️ D0 WARNING | B54: D0 thresholds: Sharpe ≥ 2.0, Fitness ≥ 1.30 — NOT VIABLE. Focus 100% on D1.
A55: 💰 Fee Note | B55: 15 alphas ACTIVE = Tier 1 (up to $3,500/mo). Fees accruing at Conditional Consultant stage.
